sparse_autoencoder/__init__.py
sparse_autoencoder/activation_resampler/__init__.py
sparse_autoencoder/activation_resampler/activation_resampler.py
sparse_autoencoder/activation_resampler/tests/test_activation_resampler.py
sparse_autoencoder/activation_resampler/utils/__init__.py
sparse_autoencoder/activation_resampler/utils/component_slice_tensor.py
sparse_autoencoder/activation_store/__init__.py
sparse_autoencoder/activation_store/base_store.py
sparse_autoencoder/activation_store/tensor_store.py
sparse_autoencoder/activation_store/tests/test_tensor_store.py
sparse_autoencoder/autoencoder/__init__.py
sparse_autoencoder/autoencoder/components/__init__.py
sparse_autoencoder/autoencoder/components/linear_encoder.py
sparse_autoencoder/autoencoder/components/tests/__snapshots__/test_linear_encoder.ambr
sparse_autoencoder/autoencoder/components/tests/test_compare_neel_implementation.py
sparse_autoencoder/autoencoder/components/tests/test_linear_encoder.py
sparse_autoencoder/autoencoder/components/tests/test_tied_bias.py
sparse_autoencoder/autoencoder/components/tests/test_unit_norm_decoder.py
sparse_autoencoder/autoencoder/components/tied_bias.py
sparse_autoencoder/autoencoder/components/unit_norm_decoder.py
sparse_autoencoder/autoencoder/model.py
sparse_autoencoder/autoencoder/tests/__snapshots__/test_model.ambr
sparse_autoencoder/autoencoder/tests/test_model.py
sparse_autoencoder/autoencoder/types.py
sparse_autoencoder/loss/__init__.py
sparse_autoencoder/loss/abstract_loss.py
sparse_autoencoder/loss/decoded_activations_l2.py
sparse_autoencoder/loss/learned_activations_l1.py
sparse_autoencoder/loss/reducer.py
sparse_autoencoder/loss/tests/__snapshots__/test_decoded_activations_l2.ambr
sparse_autoencoder/loss/tests/test_abstract_loss.py
sparse_autoencoder/loss/tests/test_decoded_activations_l2.py
sparse_autoencoder/loss/tests/test_learned_activations_l1.py
sparse_autoencoder/loss/tests/test_neel_loss.py
sparse_autoencoder/loss/tests/test_towards_monosemanticity_loss.py
sparse_autoencoder-1.10.0.dist-info/LICENSE
sparse_autoencoder-1.10.0.dist-info/METADATA
sparse_autoencoder-1.10.0.dist-info/WHEEL
sparse_autoencoder-1.10.0.dist-info/entry_points.txt
sparse_autoencoder-1.10.0.dist-info/RECORD
