Metadata-Version: 2.1
Name: sparse_autoencoder
Version: 1.10.0
Summary: Sparse Autoencoder for Mechanistic Interpretability
License: MIT
Author: Alan Cooney
Author-email: 41682961+alan-cooney@users.noreply.github.com
Requires-Python: >=3.10,<3.12
Classifier: License :: OSI Approved :: MIT License
Classifier: Programming Language :: Python :: 3
Classifier: Programming Language :: Python :: 3.10
Classifier: Programming Language :: Python :: 3.11
Requires-Dist: datasets (>=2.16.1)
Requires-Dist: einops (>=0.7.0)
Requires-Dist: pydantic (>=2.5.3)
Requires-Dist: strenum (>=0.4.15)
Requires-Dist: tokenizers (>=0.15.1)
Requires-Dist: torch (>=2.1.2)
Requires-Dist: transformers (>=4.37.1)
Requires-Dist: wandb (>=0.16.2)
Requires-Dist: zstandard (>=0.22.0)
